antiberty/AntiBERTyRunner.py
antiberty/__init__.py
antiberty/model/AntiBERTy.py
antiberty/model/DataCollatorForGrafting.py
antiberty/model/DataCollatorForSpeciesChain.py
antiberty/model/__init__.py
antiberty/model/antiberty_config.py
antiberty/model/util.py
antiberty/trained_models/vocab.txt
antiberty/trained_models/AntiBERTy_md_smooth/config.json
antiberty/trained_models/AntiBERTy_md_smooth/pytorch_model.bin
antiberty/trained_models/AntiBERTy_md_smooth/training_args.bin
antiberty/utils/__init__.py
antiberty/utils/general.py
antiberty/utils/get_weights.py
antiberty-0.1.3.dist-info/LICENSE.MD
antiberty-0.1.3.dist-info/METADATA
antiberty-0.1.3.dist-info/WHEEL
antiberty-0.1.3.dist-info/top_level.txt
antiberty-0.1.3.dist-info/RECORD
