Metadata-Version: 2.1
Name: antiberty
Version: 0.1.3
License-File: LICENSE.MD
Requires-Dist: torch (>=1.7.1)
Requires-Dist: transformers (>=4.5.1)
